workenv/__init__.py
workenv/__main__.py
workenv/actions.py
workenv/bash.py
workenv/cli.py
workenv/config.py
workenv/constants.py
workenv/io.py
workenv-2.1.1.dist-info/LICENSE
workenv-2.1.1.dist-info/METADATA
workenv-2.1.1.dist-info/WHEEL
workenv-2.1.1.dist-info/entry_points.txt
workenv-2.1.1.dist-info/top_level.txt
workenv-2.1.1.dist-info/RECORD
