Metadata-Version: 2.1
Name: workenv
Version: 2.1.1
Summary: Manage local work environments
Author-email: Richard Terry <code@radiac.net>
Project-URL: Homepage, https://radiac.net/projects/workenv/
Project-URL: Changelog, https://github.com/radiac/workenv/blob/main/changelog.rst
Project-URL: Repository, https://github.com/radiac/workenv
Project-URL: Issues, https://github.com/radiac/workenv/issues
Keywords: bash
Classifier: Development Status :: 5 - Production/Stable
Classifier: Intended Audience :: Developers
Classifier: License :: OSI Approved :: BSD License
Classifier: Operating System :: OS Independent
Classifier: Environment :: Console
Classifier: Topic :: System :: System Shells
Classifier: Programming Language :: Python
Classifier: Programming Language :: Python :: 3
Requires-Python: >=3.8
License-File: LICENSE
Requires-Dist: pyyaml
